test/__init__.py
test/test_unk_vocab.py
test/test_vocab.py
vocab/__init__.py
vocab/unk_vocab.py
vocab/vocab.py
vocab-0.0.5.dist-info/LICENSE
vocab-0.0.5.dist-info/METADATA
vocab-0.0.5.dist-info/WHEEL
vocab-0.0.5.dist-info/top_level.txt
vocab-0.0.5.dist-info/RECORD
